uipath_connectors/snowflake_snowflake/__init__.py
uipath_connectors/snowflake_snowflake/client.py
uipath_connectors/snowflake_snowflake/errors.py
uipath_connectors/snowflake_snowflake/py.typed
uipath_connectors/snowflake_snowflake/types.py
uipath_connectors/snowflake_snowflake/api/__init__.py
uipath_connectors/snowflake_snowflake/api/execute_async_query/__init__.py
uipath_connectors/snowflake_snowflake/api/execute_async_query/execute_async_query.py
uipath_connectors/snowflake_snowflake/api/execute_query/__init__.py
uipath_connectors/snowflake_snowflake/api/execute_query/execute_query.py
uipath_connectors/snowflake_snowflake/api/query_execution_results/__init__.py
uipath_connectors/snowflake_snowflake/api/query_execution_results/get_query_execution_results.py
uipath_connectors/snowflake_snowflake/api/query_execution_status/__init__.py
uipath_connectors/snowflake_snowflake/api/query_execution_status/get_query_execution_status.py
uipath_connectors/snowflake_snowflake/models/__init__.py
uipath_connectors/snowflake_snowflake/models/default_error.py
uipath_connectors/snowflake_snowflake/models/execute_async_query_request.py
uipath_connectors/snowflake_snowflake/models/execute_async_query_response.py
uipath_connectors/snowflake_snowflake/models/execute_query_request.py
uipath_connectors/snowflake_snowflake/models/get_query_execution_status_response.py
uipath_connectors/snowflake_snowflake/models/get_query_execution_status_response_status.py
uipath_connectors_snowflake_snowflake-1.11.0.dev12.dist-info/METADATA
uipath_connectors_snowflake_snowflake-1.11.0.dev12.dist-info/WHEEL
uipath_connectors_snowflake_snowflake-1.11.0.dev12.dist-info/entry_points.txt
uipath_connectors_snowflake_snowflake-1.11.0.dev12.dist-info/top_level.txt
uipath_connectors_snowflake_snowflake-1.11.0.dev12.dist-info/RECORD
