Metadata-Version: 2.4
Name: uipath_connectors.snowflake_snowflake
Version: 1.11.0.dev12
Summary: A client library for accessing Snowflake
Maintainer-email: Marius Cosareanu <marius.cosareanu@uipath.com>, Cristian Pufu <cristian.pufu@uipath.com>
Project-URL: Homepage, https://uipath.com
Classifier: Development Status :: 3 - Alpha
Classifier: Intended Audience :: Developers
Classifier: Topic :: Software Development :: Build Tools
Classifier: Programming Language :: Python :: 3.9
Classifier: Programming Language :: Python :: 3.10
Classifier: Programming Language :: Python :: 3.11
Classifier: Programming Language :: Python :: 3.12
Requires-Python: >=3.9
Requires-Dist: httpx>=0.20.0
Requires-Dist: attrs>=22.2.0
Requires-Dist: python-dateutil>=2.8.0
Requires-Dist: uipath_sdk>=0.0.72
